experiment_buddy/__init__.py
experiment_buddy/executors.py
experiment_buddy/experiment_buddy.py
experiment_buddy/utils.py
experiment_buddy/buddy_init/__init__.py
experiment_buddy/buddy_init/init_actions.py
experiment_buddy/buddy_init/init_project.py
scripts/docker/run_experiment.sh
scripts/general/run_experiment.sh
scripts/general/run_sweep.sh
scripts/hydra/run_experiment.sh
scripts/hydra/run_sweep.sh
scripts/slurm/run_experiment.sh
scripts/slurm/run_sweep.sh
scripts/slurm/srun_python.sh
experiment_buddy-0.0.22.dist-info/LICENSE
experiment_buddy-0.0.22.dist-info/METADATA
experiment_buddy-0.0.22.dist-info/WHEEL
experiment_buddy-0.0.22.dist-info/entry_points.txt
experiment_buddy-0.0.22.dist-info/top_level.txt
experiment_buddy-0.0.22.dist-info/RECORD
