Metadata-Version: 2.1
Name: experiment-buddy
Version: 0.0.22
Home-page: https://github.com/ministry-of-silly-code/experiment_buddy/
Author: Manuel Del Verme, Ionelia Buzatu, Simone Totaro
Author-email: 
Maintainer: Manuel Del Verme
License-File: LICENSE
Requires-Dist: GitPython
Requires-Dist: tensorboardX
Requires-Dist: matplotlib
Requires-Dist: wandb
Requires-Dist: fabric
Requires-Dist: cloudpickle
Requires-Dist: PyYaml
Requires-Dist: paramiko
Requires-Dist: tqdm
Requires-Dist: aiohttp
